sandbox_func/__init__.py
sandbox_func/__main__.py
sandbox_func/common/__init__.py
sandbox_func/common/config/BaseURLConfig.py
sandbox_func/common/config/BusinessURLConfig.py
sandbox_func/common/config/ConfigModel.py
sandbox_func/common/config/LogConfig.py
sandbox_func/common/config/LoginConfig.py
sandbox_func/common/config/TencentConfig.py
sandbox_func/common/config/__init__.py
sandbox_func/common/file/CosFileManager.py
sandbox_func/common/file/__init__.py
sandbox_func/common/lang/__init__.py
sandbox_func/common/lang/async_requests.py
sandbox_func/common/lang/dictclass.py
sandbox_func/common/lang/logger_setting.py
sandbox_func/common/lang/moduleutil.py
sandbox_func/common/lang/singleton.py
sandbox_func/common/local/__init__.py
sandbox_func/common/local/clientinfo.py
sandbox_func/common/log/AwLogger.py
sandbox_func/common/log/LogManager.py
sandbox_func/common/log/__init__.py
sandbox_func/common/request/CybotronClient.py
sandbox_func/common/request/CybotronSyncClient.py
sandbox_func/common/request/__init__.py
sandbox_func/model/SandboxApp.py
sandbox_func/model/SandboxFunc.py
sandbox_func/model/SandboxFuncManager.py
sandbox_func/model/SandboxProjManager.py
sandbox_func/model/SandboxRepo.py
sandbox_func/model/__init__.py
sandbox_func/repository/__init__.py
sandbox_func/repository/cybotron/__init__.py
sandbox_func/repository/cybotron/model/__init__.py
sandbox_func/repository/cybotron/model/metadataobj.py
sandbox_func/repository/cybotron/service/__init__.py
sandbox_func/repository/cybotron/service/common_access.py
sandbox_func/repository/cybotron/service/data_accessor.py
sandbox_func/repository/cybotron/service/metadata_accessor.py
sandbox_func/repository/cybotron/service/sandbox_accessor.py
sandbox_func/request/SFCallback.py
sandbox_func/request/SFEventRequest.py
sandbox_func/request/SFExtRequest.py
sandbox_func/request/SFRequest.py
sandbox_func/request/SFResponse.py
sandbox_func/request/SFResponseJob.py
sandbox_func/request/SFWebRequest.py
sandbox_func-0.1.4.dist-info/METADATA
sandbox_func-0.1.4.dist-info/WHEEL
sandbox_func-0.1.4.dist-info/top_level.txt
sandbox_func-0.1.4.dist-info/RECORD
